{"appleSKU":"","appleTeamID":"","enableCodelessAutoInitialization":true,"enableUnityGamingServicesAutoInitialization":false,"products":[{"id":"100_stars","type":0,"storeIDs":[],"defaultDescription":{"googleLocale":4,"title":"100 Stars","description":"Gives 100 stars to the player"},"screenshotPath":"","applePriceTier":0,"googlePrice":{"data":[0,0,0,0],"num":0.0},"pricingTemplateID":"","descriptions":[],"udpPrice":{"data":[0,0,0,0],"num":0.0},"payouts":[{"t":"Currency","st":"","q":100.0,"d":""}]},{"id":"300_stars","type":0,"storeIDs":[],"defaultDescription":{"googleLocale":4,"title":"300 stars","description":"Gives 300 stars to the player"},"screenshotPath":"","applePriceTier":0,"googlePrice":{"data":[0,0,0,0],"num":0.0},"pricingTemplateID":"","descriptions":[],"udpPrice":{"data":[0,0,0,0],"num":0.0},"payouts":[{"t":"Currency","st":"","q":300.0,"d":""}]},{"id":"500_stars","type":0,"storeIDs":[],"defaultDescription":{"googleLocale":4,"title":"500 stars","description":"Gives 500 stars to the player"},"screenshotPath":"","applePriceTier":0,"googlePrice":{"data":[0,0,0,0],"num":0.0},"pricingTemplateID":"","descriptions":[],"udpPrice":{"data":[0,0,0,0],"num":0.0},"payouts":[{"t":"Currency","st":"","q":500.0,"d":""}]},{"id":"all_cars","type":1,"storeIDs":[],"defaultDescription":{"googleLocale":4,"title":"All cars","description":"User unlocks all cars"},"screenshotPath":"","applePriceTier":0,"googlePrice":{"data":[0,0,0,0],"num":0.0},"pricingTemplateID":"","descriptions":[],"udpPrice":{"data":[0,0,0,0],"num":0.0},"payouts":[]},{"id":"all_maps","type":1,"storeIDs":[],"defaultDescription":{"googleLocale":4,"title":"All maps","description":"User unlocks all maps"},"screenshotPath":"","applePriceTier":0,"googlePrice":{"data":[0,0,0,0],"num":0.0},"pricingTemplateID":"","descriptions":[],"udpPrice":{"data":[0,0,0,0],"num":0.0},"payouts":[]},{"id":"all_cars_maps","type":1,"storeIDs":[],"defaultDescription":{"googleLocale":4,"title":"All cars and maps","description":"User unlocks all cars and maps"},"screenshotPath":"","applePriceTier":0,"googlePrice":{"data":[0,0,0,0],"num":0.0},"pricingTemplateID":"","descriptions":[],"udpPrice":{"data":[0,0,0,0],"num":0.0},"payouts":[]},{"id":"no_banner_ads","type":1,"storeIDs":[],"defaultDescription":{"googleLocale":4,"title":"Delete All BannerAds","description":"Delete All BannerAds"},"screenshotPath":"","applePriceTier":0,"googlePrice":{"data":[0,0,0,0],"num":0.0},"pricingTemplateID":"","descriptions":[],"udpPrice":{"data":[0,0,0,0],"num":0.0},"payouts":[]}]}